{
  "schemaVersion": 2,
  "key": "language",
  "name": "Language",
  "decks": [
    {
      "key": "essential-chinese",
      "name": "Essential Chinese",
      "description": "Mandarin from absolute zero, structured the way spaced-repetition research says to learn a language: the tone and pinyin system first, then day-one survival phrases, then the highest-frequency words, then the grammar patterns that snap them together. Characters ride up front with tap-to-hear speech, pinyin and usage notes appear on every reveal, and the phrases you must be able to say are trained in both directions. Simplified characters. Keep new cards to 5-10 a day and say every answer out loud.",
      "cardCount": 293,
      "topics": [
        "chinese",
        "mandarin",
        "language",
        "beginner",
        "pinyin"
      ],
      "coverImage": "https://flagcdn.com/w640/cn.png"
    },
    {
      "key": "essential-spanish",
      "name": "Essential Spanish",
      "description": "Your first weeks of Spanish, front-loaded for payoff: survival phrases you can use on day one, then the highest-frequency vocabulary (numbers, time words, question words, the 25 most useful verbs, family, food, places) trained in both directions, plus the ser, estar, and tener conjugations. Latin American Spanish by default.",
      "cardCount": 413,
      "topics": [
        "spanish",
        "language",
        "vocabulary"
      ],
      "coverImage": "https://flagcdn.com/w640/es.png"
    }
  ]
}
