{
  "key": "kanto-pokedex",
  "version": 1,
  "name": "Kanto Pokédex: The Original 151",
  "description": "All 151 Pokémon from the original Kanto Pokédex, with official artwork. Name each one from its picture; answers include Pokédex number and type.",
  "category": "Pop Culture",
  "topics": [
    "pokemon",
    "games",
    "trivia"
  ],
  "coverImage": "https://raw.githubusercontent.com/PokeAPI/sprites/master/sprites/pokemon/other/official-artwork/25.png",
  "ttsLang": null,
  "notes": [
    {
      "key": "bulbasaur",
      "model": "basic",
      "fields": {
        "front": "Who's that Pokémon?",
        "back": "Bulbasaur",
        "extra": "#001 · Grass/Poison",
        "frontImage": "https://raw.githubusercontent.com/PokeAPI/sprites/master/sprites/pokemon/other/official-artwork/1.png"
      },
      "tags": [
        "poke::grass"
      ]
    },
    {
      "key": "ivysaur",
      "model": "basic",
      "fields": {
        "front": "Who's that Pokémon?",
        "back": "Ivysaur",
        "extra": "#002 · Grass/Poison",
        "frontImage": "https://raw.githubusercontent.com/PokeAPI/sprites/master/sprites/pokemon/other/official-artwork/2.png"
      },
      "tags": [
        "poke::grass"
      ]
    },
    {
      "key": "venusaur",
      "model": "basic",
      "fields": {
        "front": "Who's that Pokémon?",
        "back": "Venusaur",
        "extra": "#003 · Grass/Poison",
        "frontImage": "https://raw.githubusercontent.com/PokeAPI/sprites/master/sprites/pokemon/other/official-artwork/3.png"
      },
      "tags": [
        "poke::grass"
      ]
    },
    {
      "key": "charmander",
      "model": "basic",
      "fields": {
        "front": "Who's that Pokémon?",
        "back": "Charmander",
        "extra": "#004 · Fire",
        "frontImage": "https://raw.githubusercontent.com/PokeAPI/sprites/master/sprites/pokemon/other/official-artwork/4.png"
      },
      "tags": [
        "poke::fire"
      ]
    },
    {
      "key": "charmeleon",
      "model": "basic",
      "fields": {
        "front": "Who's that Pokémon?",
        "back": "Charmeleon",
        "extra": "#005 · Fire",
        "frontImage": "https://raw.githubusercontent.com/PokeAPI/sprites/master/sprites/pokemon/other/official-artwork/5.png"
      },
      "tags": [
        "poke::fire"
      ]
    },
    {
      "key": "charizard",
      "model": "basic",
      "fields": {
        "front": "Who's that Pokémon?",
        "back": "Charizard",
        "extra": "#006 · Fire/Flying",
        "frontImage": "https://raw.githubusercontent.com/PokeAPI/sprites/master/sprites/pokemon/other/official-artwork/6.png"
      },
      "tags": [
        "poke::fire"
      ]
    },
    {
      "key": "squirtle",
      "model": "basic",
      "fields": {
        "front": "Who's that Pokémon?",
        "back": "Squirtle",
        "extra": "#007 · Water",
        "frontImage": "https://raw.githubusercontent.com/PokeAPI/sprites/master/sprites/pokemon/other/official-artwork/7.png"
      },
      "tags": [
        "poke::water"
      ]
    },
    {
      "key": "wartortle",
      "model": "basic",
      "fields": {
        "front": "Who's that Pokémon?",
        "back": "Wartortle",
        "extra": "#008 · Water",
        "frontImage": "https://raw.githubusercontent.com/PokeAPI/sprites/master/sprites/pokemon/other/official-artwork/8.png"
      },
      "tags": [
        "poke::water"
      ]
    },
    {
      "key": "blastoise",
      "model": "basic",
      "fields": {
        "front": "Who's that Pokémon?",
        "back": "Blastoise",
        "extra": "#009 · Water",
        "frontImage": "https://raw.githubusercontent.com/PokeAPI/sprites/master/sprites/pokemon/other/official-artwork/9.png"
      },
      "tags": [
        "poke::water"
      ]
    },
    {
      "key": "caterpie",
      "model": "basic",
      "fields": {
        "front": "Who's that Pokémon?",
        "back": "Caterpie",
        "extra": "#010 · Bug",
        "frontImage": "https://raw.githubusercontent.com/PokeAPI/sprites/master/sprites/pokemon/other/official-artwork/10.png"
      },
      "tags": [
        "poke::bug"
      ]
    },
    {
      "key": "metapod",
      "model": "basic",
      "fields": {
        "front": "Who's that Pokémon?",
        "back": "Metapod",
        "extra": "#011 · Bug",
        "frontImage": "https://raw.githubusercontent.com/PokeAPI/sprites/master/sprites/pokemon/other/official-artwork/11.png"
      },
      "tags": [
        "poke::bug"
      ]
    },
    {
      "key": "butterfree",
      "model": "basic",
      "fields": {
        "front": "Who's that Pokémon?",
        "back": "Butterfree",
        "extra": "#012 · Bug/Flying",
        "frontImage": "https://raw.githubusercontent.com/PokeAPI/sprites/master/sprites/pokemon/other/official-artwork/12.png"
      },
      "tags": [
        "poke::bug"
      ]
    },
    {
      "key": "weedle",
      "model": "basic",
      "fields": {
        "front": "Who's that Pokémon?",
        "back": "Weedle",
        "extra": "#013 · Bug/Poison",
        "frontImage": "https://raw.githubusercontent.com/PokeAPI/sprites/master/sprites/pokemon/other/official-artwork/13.png"
      },
      "tags": [
        "poke::bug"
      ]
    },
    {
      "key": "kakuna",
      "model": "basic",
      "fields": {
        "front": "Who's that Pokémon?",
        "back": "Kakuna",
        "extra": "#014 · Bug/Poison",
        "frontImage": "https://raw.githubusercontent.com/PokeAPI/sprites/master/sprites/pokemon/other/official-artwork/14.png"
      },
      "tags": [
        "poke::bug"
      ]
    },
    {
      "key": "beedrill",
      "model": "basic",
      "fields": {
        "front": "Who's that Pokémon?",
        "back": "Beedrill",
        "extra": "#015 · Bug/Poison",
        "frontImage": "https://raw.githubusercontent.com/PokeAPI/sprites/master/sprites/pokemon/other/official-artwork/15.png"
      },
      "tags": [
        "poke::bug"
      ]
    },
    {
      "key": "pidgey",
      "model": "basic",
      "fields": {
        "front": "Who's that Pokémon?",
        "back": "Pidgey",
        "extra": "#016 · Normal/Flying",
        "frontImage": "https://raw.githubusercontent.com/PokeAPI/sprites/master/sprites/pokemon/other/official-artwork/16.png"
      },
      "tags": [
        "poke::normal"
      ]
    },
    {
      "key": "pidgeotto",
      "model": "basic",
      "fields": {
        "front": "Who's that Pokémon?",
        "back": "Pidgeotto",
        "extra": "#017 · Normal/Flying",
        "frontImage": "https://raw.githubusercontent.com/PokeAPI/sprites/master/sprites/pokemon/other/official-artwork/17.png"
      },
      "tags": [
        "poke::normal"
      ]
    },
    {
      "key": "pidgeot",
      "model": "basic",
      "fields": {
        "front": "Who's that Pokémon?",
        "back": "Pidgeot",
        "extra": "#018 · Normal/Flying",
        "frontImage": "https://raw.githubusercontent.com/PokeAPI/sprites/master/sprites/pokemon/other/official-artwork/18.png"
      },
      "tags": [
        "poke::normal"
      ]
    },
    {
      "key": "rattata",
      "model": "basic",
      "fields": {
        "front": "Who's that Pokémon?",
        "back": "Rattata",
        "extra": "#019 · Normal",
        "frontImage": "https://raw.githubusercontent.com/PokeAPI/sprites/master/sprites/pokemon/other/official-artwork/19.png"
      },
      "tags": [
        "poke::normal"
      ]
    },
    {
      "key": "raticate",
      "model": "basic",
      "fields": {
        "front": "Who's that Pokémon?",
        "back": "Raticate",
        "extra": "#020 · Normal",
        "frontImage": "https://raw.githubusercontent.com/PokeAPI/sprites/master/sprites/pokemon/other/official-artwork/20.png"
      },
      "tags": [
        "poke::normal"
      ]
    },
    {
      "key": "spearow",
      "model": "basic",
      "fields": {
        "front": "Who's that Pokémon?",
        "back": "Spearow",
        "extra": "#021 · Normal/Flying",
        "frontImage": "https://raw.githubusercontent.com/PokeAPI/sprites/master/sprites/pokemon/other/official-artwork/21.png"
      },
      "tags": [
        "poke::normal"
      ]
    },
    {
      "key": "fearow",
      "model": "basic",
      "fields": {
        "front": "Who's that Pokémon?",
        "back": "Fearow",
        "extra": "#022 · Normal/Flying",
        "frontImage": "https://raw.githubusercontent.com/PokeAPI/sprites/master/sprites/pokemon/other/official-artwork/22.png"
      },
      "tags": [
        "poke::normal"
      ]
    },
    {
      "key": "ekans",
      "model": "basic",
      "fields": {
        "front": "Who's that Pokémon?",
        "back": "Ekans",
        "extra": "#023 · Poison",
        "frontImage": "https://raw.githubusercontent.com/PokeAPI/sprites/master/sprites/pokemon/other/official-artwork/23.png"
      },
      "tags": [
        "poke::poison"
      ]
    },
    {
      "key": "arbok",
      "model": "basic",
      "fields": {
        "front": "Who's that Pokémon?",
        "back": "Arbok",
        "extra": "#024 · Poison",
        "frontImage": "https://raw.githubusercontent.com/PokeAPI/sprites/master/sprites/pokemon/other/official-artwork/24.png"
      },
      "tags": [
        "poke::poison"
      ]
    },
    {
      "key": "pikachu",
      "model": "basic",
      "fields": {
        "front": "Who's that Pokémon?",
        "back": "Pikachu",
        "extra": "#025 · Electric",
        "frontImage": "https://raw.githubusercontent.com/PokeAPI/sprites/master/sprites/pokemon/other/official-artwork/25.png"
      },
      "tags": [
        "poke::electric"
      ]
    },
    {
      "key": "raichu",
      "model": "basic",
      "fields": {
        "front": "Who's that Pokémon?",
        "back": "Raichu",
        "extra": "#026 · Electric",
        "frontImage": "https://raw.githubusercontent.com/PokeAPI/sprites/master/sprites/pokemon/other/official-artwork/26.png"
      },
      "tags": [
        "poke::electric"
      ]
    },
    {
      "key": "sandshrew",
      "model": "basic",
      "fields": {
        "front": "Who's that Pokémon?",
        "back": "Sandshrew",
        "extra": "#027 · Ground",
        "frontImage": "https://raw.githubusercontent.com/PokeAPI/sprites/master/sprites/pokemon/other/official-artwork/27.png"
      },
      "tags": [
        "poke::ground"
      ]
    },
    {
      "key": "sandslash",
      "model": "basic",
      "fields": {
        "front": "Who's that Pokémon?",
        "back": "Sandslash",
        "extra": "#028 · Ground",
        "frontImage": "https://raw.githubusercontent.com/PokeAPI/sprites/master/sprites/pokemon/other/official-artwork/28.png"
      },
      "tags": [
        "poke::ground"
      ]
    },
    {
      "key": "nidoran-f",
      "model": "basic",
      "fields": {
        "front": "Who's that Pokémon?",
        "back": "Nidoran♀",
        "extra": "#029 · Poison",
        "frontImage": "https://raw.githubusercontent.com/PokeAPI/sprites/master/sprites/pokemon/other/official-artwork/29.png"
      },
      "tags": [
        "poke::poison"
      ]
    },
    {
      "key": "nidorina",
      "model": "basic",
      "fields": {
        "front": "Who's that Pokémon?",
        "back": "Nidorina",
        "extra": "#030 · Poison",
        "frontImage": "https://raw.githubusercontent.com/PokeAPI/sprites/master/sprites/pokemon/other/official-artwork/30.png"
      },
      "tags": [
        "poke::poison"
      ]
    },
    {
      "key": "nidoqueen",
      "model": "basic",
      "fields": {
        "front": "Who's that Pokémon?",
        "back": "Nidoqueen",
        "extra": "#031 · Poison/Ground",
        "frontImage": "https://raw.githubusercontent.com/PokeAPI/sprites/master/sprites/pokemon/other/official-artwork/31.png"
      },
      "tags": [
        "poke::poison"
      ]
    },
    {
      "key": "nidoran-m",
      "model": "basic",
      "fields": {
        "front": "Who's that Pokémon?",
        "back": "Nidoran♂",
        "extra": "#032 · Poison",
        "frontImage": "https://raw.githubusercontent.com/PokeAPI/sprites/master/sprites/pokemon/other/official-artwork/32.png"
      },
      "tags": [
        "poke::poison"
      ]
    },
    {
      "key": "nidorino",
      "model": "basic",
      "fields": {
        "front": "Who's that Pokémon?",
        "back": "Nidorino",
        "extra": "#033 · Poison",
        "frontImage": "https://raw.githubusercontent.com/PokeAPI/sprites/master/sprites/pokemon/other/official-artwork/33.png"
      },
      "tags": [
        "poke::poison"
      ]
    },
    {
      "key": "nidoking",
      "model": "basic",
      "fields": {
        "front": "Who's that Pokémon?",
        "back": "Nidoking",
        "extra": "#034 · Poison/Ground",
        "frontImage": "https://raw.githubusercontent.com/PokeAPI/sprites/master/sprites/pokemon/other/official-artwork/34.png"
      },
      "tags": [
        "poke::poison"
      ]
    },
    {
      "key": "clefairy",
      "model": "basic",
      "fields": {
        "front": "Who's that Pokémon?",
        "back": "Clefairy",
        "extra": "#035 · Fairy",
        "frontImage": "https://raw.githubusercontent.com/PokeAPI/sprites/master/sprites/pokemon/other/official-artwork/35.png"
      },
      "tags": [
        "poke::fairy"
      ]
    },
    {
      "key": "clefable",
      "model": "basic",
      "fields": {
        "front": "Who's that Pokémon?",
        "back": "Clefable",
        "extra": "#036 · Fairy",
        "frontImage": "https://raw.githubusercontent.com/PokeAPI/sprites/master/sprites/pokemon/other/official-artwork/36.png"
      },
      "tags": [
        "poke::fairy"
      ]
    },
    {
      "key": "vulpix",
      "model": "basic",
      "fields": {
        "front": "Who's that Pokémon?",
        "back": "Vulpix",
        "extra": "#037 · Fire",
        "frontImage": "https://raw.githubusercontent.com/PokeAPI/sprites/master/sprites/pokemon/other/official-artwork/37.png"
      },
      "tags": [
        "poke::fire"
      ]
    },
    {
      "key": "ninetales",
      "model": "basic",
      "fields": {
        "front": "Who's that Pokémon?",
        "back": "Ninetales",
        "extra": "#038 · Fire",
        "frontImage": "https://raw.githubusercontent.com/PokeAPI/sprites/master/sprites/pokemon/other/official-artwork/38.png"
      },
      "tags": [
        "poke::fire"
      ]
    },
    {
      "key": "jigglypuff",
      "model": "basic",
      "fields": {
        "front": "Who's that Pokémon?",
        "back": "Jigglypuff",
        "extra": "#039 · Normal/Fairy",
        "frontImage": "https://raw.githubusercontent.com/PokeAPI/sprites/master/sprites/pokemon/other/official-artwork/39.png"
      },
      "tags": [
        "poke::normal"
      ]
    },
    {
      "key": "wigglytuff",
      "model": "basic",
      "fields": {
        "front": "Who's that Pokémon?",
        "back": "Wigglytuff",
        "extra": "#040 · Normal/Fairy",
        "frontImage": "https://raw.githubusercontent.com/PokeAPI/sprites/master/sprites/pokemon/other/official-artwork/40.png"
      },
      "tags": [
        "poke::normal"
      ]
    },
    {
      "key": "zubat",
      "model": "basic",
      "fields": {
        "front": "Who's that Pokémon?",
        "back": "Zubat",
        "extra": "#041 · Poison/Flying",
        "frontImage": "https://raw.githubusercontent.com/PokeAPI/sprites/master/sprites/pokemon/other/official-artwork/41.png"
      },
      "tags": [
        "poke::poison"
      ]
    },
    {
      "key": "golbat",
      "model": "basic",
      "fields": {
        "front": "Who's that Pokémon?",
        "back": "Golbat",
        "extra": "#042 · Poison/Flying",
        "frontImage": "https://raw.githubusercontent.com/PokeAPI/sprites/master/sprites/pokemon/other/official-artwork/42.png"
      },
      "tags": [
        "poke::poison"
      ]
    },
    {
      "key": "oddish",
      "model": "basic",
      "fields": {
        "front": "Who's that Pokémon?",
        "back": "Oddish",
        "extra": "#043 · Grass/Poison",
        "frontImage": "https://raw.githubusercontent.com/PokeAPI/sprites/master/sprites/pokemon/other/official-artwork/43.png"
      },
      "tags": [
        "poke::grass"
      ]
    },
    {
      "key": "gloom",
      "model": "basic",
      "fields": {
        "front": "Who's that Pokémon?",
        "back": "Gloom",
        "extra": "#044 · Grass/Poison",
        "frontImage": "https://raw.githubusercontent.com/PokeAPI/sprites/master/sprites/pokemon/other/official-artwork/44.png"
      },
      "tags": [
        "poke::grass"
      ]
    },
    {
      "key": "vileplume",
      "model": "basic",
      "fields": {
        "front": "Who's that Pokémon?",
        "back": "Vileplume",
        "extra": "#045 · Grass/Poison",
        "frontImage": "https://raw.githubusercontent.com/PokeAPI/sprites/master/sprites/pokemon/other/official-artwork/45.png"
      },
      "tags": [
        "poke::grass"
      ]
    },
    {
      "key": "paras",
      "model": "basic",
      "fields": {
        "front": "Who's that Pokémon?",
        "back": "Paras",
        "extra": "#046 · Bug/Grass",
        "frontImage": "https://raw.githubusercontent.com/PokeAPI/sprites/master/sprites/pokemon/other/official-artwork/46.png"
      },
      "tags": [
        "poke::bug"
      ]
    },
    {
      "key": "parasect",
      "model": "basic",
      "fields": {
        "front": "Who's that Pokémon?",
        "back": "Parasect",
        "extra": "#047 · Bug/Grass",
        "frontImage": "https://raw.githubusercontent.com/PokeAPI/sprites/master/sprites/pokemon/other/official-artwork/47.png"
      },
      "tags": [
        "poke::bug"
      ]
    },
    {
      "key": "venonat",
      "model": "basic",
      "fields": {
        "front": "Who's that Pokémon?",
        "back": "Venonat",
        "extra": "#048 · Bug/Poison",
        "frontImage": "https://raw.githubusercontent.com/PokeAPI/sprites/master/sprites/pokemon/other/official-artwork/48.png"
      },
      "tags": [
        "poke::bug"
      ]
    },
    {
      "key": "venomoth",
      "model": "basic",
      "fields": {
        "front": "Who's that Pokémon?",
        "back": "Venomoth",
        "extra": "#049 · Bug/Poison",
        "frontImage": "https://raw.githubusercontent.com/PokeAPI/sprites/master/sprites/pokemon/other/official-artwork/49.png"
      },
      "tags": [
        "poke::bug"
      ]
    },
    {
      "key": "diglett",
      "model": "basic",
      "fields": {
        "front": "Who's that Pokémon?",
        "back": "Diglett",
        "extra": "#050 · Ground",
        "frontImage": "https://raw.githubusercontent.com/PokeAPI/sprites/master/sprites/pokemon/other/official-artwork/50.png"
      },
      "tags": [
        "poke::ground"
      ]
    },
    {
      "key": "dugtrio",
      "model": "basic",
      "fields": {
        "front": "Who's that Pokémon?",
        "back": "Dugtrio",
        "extra": "#051 · Ground",
        "frontImage": "https://raw.githubusercontent.com/PokeAPI/sprites/master/sprites/pokemon/other/official-artwork/51.png"
      },
      "tags": [
        "poke::ground"
      ]
    },
    {
      "key": "meowth",
      "model": "basic",
      "fields": {
        "front": "Who's that Pokémon?",
        "back": "Meowth",
        "extra": "#052 · Normal",
        "frontImage": "https://raw.githubusercontent.com/PokeAPI/sprites/master/sprites/pokemon/other/official-artwork/52.png"
      },
      "tags": [
        "poke::normal"
      ]
    },
    {
      "key": "persian",
      "model": "basic",
      "fields": {
        "front": "Who's that Pokémon?",
        "back": "Persian",
        "extra": "#053 · Normal",
        "frontImage": "https://raw.githubusercontent.com/PokeAPI/sprites/master/sprites/pokemon/other/official-artwork/53.png"
      },
      "tags": [
        "poke::normal"
      ]
    },
    {
      "key": "psyduck",
      "model": "basic",
      "fields": {
        "front": "Who's that Pokémon?",
        "back": "Psyduck",
        "extra": "#054 · Water",
        "frontImage": "https://raw.githubusercontent.com/PokeAPI/sprites/master/sprites/pokemon/other/official-artwork/54.png"
      },
      "tags": [
        "poke::water"
      ]
    },
    {
      "key": "golduck",
      "model": "basic",
      "fields": {
        "front": "Who's that Pokémon?",
        "back": "Golduck",
        "extra": "#055 · Water",
        "frontImage": "https://raw.githubusercontent.com/PokeAPI/sprites/master/sprites/pokemon/other/official-artwork/55.png"
      },
      "tags": [
        "poke::water"
      ]
    },
    {
      "key": "mankey",
      "model": "basic",
      "fields": {
        "front": "Who's that Pokémon?",
        "back": "Mankey",
        "extra": "#056 · Fighting",
        "frontImage": "https://raw.githubusercontent.com/PokeAPI/sprites/master/sprites/pokemon/other/official-artwork/56.png"
      },
      "tags": [
        "poke::fighting"
      ]
    },
    {
      "key": "primeape",
      "model": "basic",
      "fields": {
        "front": "Who's that Pokémon?",
        "back": "Primeape",
        "extra": "#057 · Fighting",
        "frontImage": "https://raw.githubusercontent.com/PokeAPI/sprites/master/sprites/pokemon/other/official-artwork/57.png"
      },
      "tags": [
        "poke::fighting"
      ]
    },
    {
      "key": "growlithe",
      "model": "basic",
      "fields": {
        "front": "Who's that Pokémon?",
        "back": "Growlithe",
        "extra": "#058 · Fire",
        "frontImage": "https://raw.githubusercontent.com/PokeAPI/sprites/master/sprites/pokemon/other/official-artwork/58.png"
      },
      "tags": [
        "poke::fire"
      ]
    },
    {
      "key": "arcanine",
      "model": "basic",
      "fields": {
        "front": "Who's that Pokémon?",
        "back": "Arcanine",
        "extra": "#059 · Fire",
        "frontImage": "https://raw.githubusercontent.com/PokeAPI/sprites/master/sprites/pokemon/other/official-artwork/59.png"
      },
      "tags": [
        "poke::fire"
      ]
    },
    {
      "key": "poliwag",
      "model": "basic",
      "fields": {
        "front": "Who's that Pokémon?",
        "back": "Poliwag",
        "extra": "#060 · Water",
        "frontImage": "https://raw.githubusercontent.com/PokeAPI/sprites/master/sprites/pokemon/other/official-artwork/60.png"
      },
      "tags": [
        "poke::water"
      ]
    },
    {
      "key": "poliwhirl",
      "model": "basic",
      "fields": {
        "front": "Who's that Pokémon?",
        "back": "Poliwhirl",
        "extra": "#061 · Water",
        "frontImage": "https://raw.githubusercontent.com/PokeAPI/sprites/master/sprites/pokemon/other/official-artwork/61.png"
      },
      "tags": [
        "poke::water"
      ]
    },
    {
      "key": "poliwrath",
      "model": "basic",
      "fields": {
        "front": "Who's that Pokémon?",
        "back": "Poliwrath",
        "extra": "#062 · Water/Fighting",
        "frontImage": "https://raw.githubusercontent.com/PokeAPI/sprites/master/sprites/pokemon/other/official-artwork/62.png"
      },
      "tags": [
        "poke::water"
      ]
    },
    {
      "key": "abra",
      "model": "basic",
      "fields": {
        "front": "Who's that Pokémon?",
        "back": "Abra",
        "extra": "#063 · Psychic",
        "frontImage": "https://raw.githubusercontent.com/PokeAPI/sprites/master/sprites/pokemon/other/official-artwork/63.png"
      },
      "tags": [
        "poke::psychic"
      ]
    },
    {
      "key": "kadabra",
      "model": "basic",
      "fields": {
        "front": "Who's that Pokémon?",
        "back": "Kadabra",
        "extra": "#064 · Psychic",
        "frontImage": "https://raw.githubusercontent.com/PokeAPI/sprites/master/sprites/pokemon/other/official-artwork/64.png"
      },
      "tags": [
        "poke::psychic"
      ]
    },
    {
      "key": "alakazam",
      "model": "basic",
      "fields": {
        "front": "Who's that Pokémon?",
        "back": "Alakazam",
        "extra": "#065 · Psychic",
        "frontImage": "https://raw.githubusercontent.com/PokeAPI/sprites/master/sprites/pokemon/other/official-artwork/65.png"
      },
      "tags": [
        "poke::psychic"
      ]
    },
    {
      "key": "machop",
      "model": "basic",
      "fields": {
        "front": "Who's that Pokémon?",
        "back": "Machop",
        "extra": "#066 · Fighting",
        "frontImage": "https://raw.githubusercontent.com/PokeAPI/sprites/master/sprites/pokemon/other/official-artwork/66.png"
      },
      "tags": [
        "poke::fighting"
      ]
    },
    {
      "key": "machoke",
      "model": "basic",
      "fields": {
        "front": "Who's that Pokémon?",
        "back": "Machoke",
        "extra": "#067 · Fighting",
        "frontImage": "https://raw.githubusercontent.com/PokeAPI/sprites/master/sprites/pokemon/other/official-artwork/67.png"
      },
      "tags": [
        "poke::fighting"
      ]
    },
    {
      "key": "machamp",
      "model": "basic",
      "fields": {
        "front": "Who's that Pokémon?",
        "back": "Machamp",
        "extra": "#068 · Fighting",
        "frontImage": "https://raw.githubusercontent.com/PokeAPI/sprites/master/sprites/pokemon/other/official-artwork/68.png"
      },
      "tags": [
        "poke::fighting"
      ]
    },
    {
      "key": "bellsprout",
      "model": "basic",
      "fields": {
        "front": "Who's that Pokémon?",
        "back": "Bellsprout",
        "extra": "#069 · Grass/Poison",
        "frontImage": "https://raw.githubusercontent.com/PokeAPI/sprites/master/sprites/pokemon/other/official-artwork/69.png"
      },
      "tags": [
        "poke::grass"
      ]
    },
    {
      "key": "weepinbell",
      "model": "basic",
      "fields": {
        "front": "Who's that Pokémon?",
        "back": "Weepinbell",
        "extra": "#070 · Grass/Poison",
        "frontImage": "https://raw.githubusercontent.com/PokeAPI/sprites/master/sprites/pokemon/other/official-artwork/70.png"
      },
      "tags": [
        "poke::grass"
      ]
    },
    {
      "key": "victreebel",
      "model": "basic",
      "fields": {
        "front": "Who's that Pokémon?",
        "back": "Victreebel",
        "extra": "#071 · Grass/Poison",
        "frontImage": "https://raw.githubusercontent.com/PokeAPI/sprites/master/sprites/pokemon/other/official-artwork/71.png"
      },
      "tags": [
        "poke::grass"
      ]
    },
    {
      "key": "tentacool",
      "model": "basic",
      "fields": {
        "front": "Who's that Pokémon?",
        "back": "Tentacool",
        "extra": "#072 · Water/Poison",
        "frontImage": "https://raw.githubusercontent.com/PokeAPI/sprites/master/sprites/pokemon/other/official-artwork/72.png"
      },
      "tags": [
        "poke::water"
      ]
    },
    {
      "key": "tentacruel",
      "model": "basic",
      "fields": {
        "front": "Who's that Pokémon?",
        "back": "Tentacruel",
        "extra": "#073 · Water/Poison",
        "frontImage": "https://raw.githubusercontent.com/PokeAPI/sprites/master/sprites/pokemon/other/official-artwork/73.png"
      },
      "tags": [
        "poke::water"
      ]
    },
    {
      "key": "geodude",
      "model": "basic",
      "fields": {
        "front": "Who's that Pokémon?",
        "back": "Geodude",
        "extra": "#074 · Rock/Ground",
        "frontImage": "https://raw.githubusercontent.com/PokeAPI/sprites/master/sprites/pokemon/other/official-artwork/74.png"
      },
      "tags": [
        "poke::rock"
      ]
    },
    {
      "key": "graveler",
      "model": "basic",
      "fields": {
        "front": "Who's that Pokémon?",
        "back": "Graveler",
        "extra": "#075 · Rock/Ground",
        "frontImage": "https://raw.githubusercontent.com/PokeAPI/sprites/master/sprites/pokemon/other/official-artwork/75.png"
      },
      "tags": [
        "poke::rock"
      ]
    },
    {
      "key": "golem",
      "model": "basic",
      "fields": {
        "front": "Who's that Pokémon?",
        "back": "Golem",
        "extra": "#076 · Rock/Ground",
        "frontImage": "https://raw.githubusercontent.com/PokeAPI/sprites/master/sprites/pokemon/other/official-artwork/76.png"
      },
      "tags": [
        "poke::rock"
      ]
    },
    {
      "key": "ponyta",
      "model": "basic",
      "fields": {
        "front": "Who's that Pokémon?",
        "back": "Ponyta",
        "extra": "#077 · Fire",
        "frontImage": "https://raw.githubusercontent.com/PokeAPI/sprites/master/sprites/pokemon/other/official-artwork/77.png"
      },
      "tags": [
        "poke::fire"
      ]
    },
    {
      "key": "rapidash",
      "model": "basic",
      "fields": {
        "front": "Who's that Pokémon?",
        "back": "Rapidash",
        "extra": "#078 · Fire",
        "frontImage": "https://raw.githubusercontent.com/PokeAPI/sprites/master/sprites/pokemon/other/official-artwork/78.png"
      },
      "tags": [
        "poke::fire"
      ]
    },
    {
      "key": "slowpoke",
      "model": "basic",
      "fields": {
        "front": "Who's that Pokémon?",
        "back": "Slowpoke",
        "extra": "#079 · Water/Psychic",
        "frontImage": "https://raw.githubusercontent.com/PokeAPI/sprites/master/sprites/pokemon/other/official-artwork/79.png"
      },
      "tags": [
        "poke::water"
      ]
    },
    {
      "key": "slowbro",
      "model": "basic",
      "fields": {
        "front": "Who's that Pokémon?",
        "back": "Slowbro",
        "extra": "#080 · Water/Psychic",
        "frontImage": "https://raw.githubusercontent.com/PokeAPI/sprites/master/sprites/pokemon/other/official-artwork/80.png"
      },
      "tags": [
        "poke::water"
      ]
    },
    {
      "key": "magnemite",
      "model": "basic",
      "fields": {
        "front": "Who's that Pokémon?",
        "back": "Magnemite",
        "extra": "#081 · Electric/Steel",
        "frontImage": "https://raw.githubusercontent.com/PokeAPI/sprites/master/sprites/pokemon/other/official-artwork/81.png"
      },
      "tags": [
        "poke::electric"
      ]
    },
    {
      "key": "magneton",
      "model": "basic",
      "fields": {
        "front": "Who's that Pokémon?",
        "back": "Magneton",
        "extra": "#082 · Electric/Steel",
        "frontImage": "https://raw.githubusercontent.com/PokeAPI/sprites/master/sprites/pokemon/other/official-artwork/82.png"
      },
      "tags": [
        "poke::electric"
      ]
    },
    {
      "key": "farfetchd",
      "model": "basic",
      "fields": {
        "front": "Who's that Pokémon?",
        "back": "Farfetch'd",
        "extra": "#083 · Normal/Flying",
        "frontImage": "https://raw.githubusercontent.com/PokeAPI/sprites/master/sprites/pokemon/other/official-artwork/83.png"
      },
      "tags": [
        "poke::normal"
      ]
    },
    {
      "key": "doduo",
      "model": "basic",
      "fields": {
        "front": "Who's that Pokémon?",
        "back": "Doduo",
        "extra": "#084 · Normal/Flying",
        "frontImage": "https://raw.githubusercontent.com/PokeAPI/sprites/master/sprites/pokemon/other/official-artwork/84.png"
      },
      "tags": [
        "poke::normal"
      ]
    },
    {
      "key": "dodrio",
      "model": "basic",
      "fields": {
        "front": "Who's that Pokémon?",
        "back": "Dodrio",
        "extra": "#085 · Normal/Flying",
        "frontImage": "https://raw.githubusercontent.com/PokeAPI/sprites/master/sprites/pokemon/other/official-artwork/85.png"
      },
      "tags": [
        "poke::normal"
      ]
    },
    {
      "key": "seel",
      "model": "basic",
      "fields": {
        "front": "Who's that Pokémon?",
        "back": "Seel",
        "extra": "#086 · Water",
        "frontImage": "https://raw.githubusercontent.com/PokeAPI/sprites/master/sprites/pokemon/other/official-artwork/86.png"
      },
      "tags": [
        "poke::water"
      ]
    },
    {
      "key": "dewgong",
      "model": "basic",
      "fields": {
        "front": "Who's that Pokémon?",
        "back": "Dewgong",
        "extra": "#087 · Water/Ice",
        "frontImage": "https://raw.githubusercontent.com/PokeAPI/sprites/master/sprites/pokemon/other/official-artwork/87.png"
      },
      "tags": [
        "poke::water"
      ]
    },
    {
      "key": "grimer",
      "model": "basic",
      "fields": {
        "front": "Who's that Pokémon?",
        "back": "Grimer",
        "extra": "#088 · Poison",
        "frontImage": "https://raw.githubusercontent.com/PokeAPI/sprites/master/sprites/pokemon/other/official-artwork/88.png"
      },
      "tags": [
        "poke::poison"
      ]
    },
    {
      "key": "muk",
      "model": "basic",
      "fields": {
        "front": "Who's that Pokémon?",
        "back": "Muk",
        "extra": "#089 · Poison",
        "frontImage": "https://raw.githubusercontent.com/PokeAPI/sprites/master/sprites/pokemon/other/official-artwork/89.png"
      },
      "tags": [
        "poke::poison"
      ]
    },
    {
      "key": "shellder",
      "model": "basic",
      "fields": {
        "front": "Who's that Pokémon?",
        "back": "Shellder",
        "extra": "#090 · Water",
        "frontImage": "https://raw.githubusercontent.com/PokeAPI/sprites/master/sprites/pokemon/other/official-artwork/90.png"
      },
      "tags": [
        "poke::water"
      ]
    },
    {
      "key": "cloyster",
      "model": "basic",
      "fields": {
        "front": "Who's that Pokémon?",
        "back": "Cloyster",
        "extra": "#091 · Water/Ice",
        "frontImage": "https://raw.githubusercontent.com/PokeAPI/sprites/master/sprites/pokemon/other/official-artwork/91.png"
      },
      "tags": [
        "poke::water"
      ]
    },
    {
      "key": "gastly",
      "model": "basic",
      "fields": {
        "front": "Who's that Pokémon?",
        "back": "Gastly",
        "extra": "#092 · Ghost/Poison",
        "frontImage": "https://raw.githubusercontent.com/PokeAPI/sprites/master/sprites/pokemon/other/official-artwork/92.png"
      },
      "tags": [
        "poke::ghost"
      ]
    },
    {
      "key": "haunter",
      "model": "basic",
      "fields": {
        "front": "Who's that Pokémon?",
        "back": "Haunter",
        "extra": "#093 · Ghost/Poison",
        "frontImage": "https://raw.githubusercontent.com/PokeAPI/sprites/master/sprites/pokemon/other/official-artwork/93.png"
      },
      "tags": [
        "poke::ghost"
      ]
    },
    {
      "key": "gengar",
      "model": "basic",
      "fields": {
        "front": "Who's that Pokémon?",
        "back": "Gengar",
        "extra": "#094 · Ghost/Poison",
        "frontImage": "https://raw.githubusercontent.com/PokeAPI/sprites/master/sprites/pokemon/other/official-artwork/94.png"
      },
      "tags": [
        "poke::ghost"
      ]
    },
    {
      "key": "onix",
      "model": "basic",
      "fields": {
        "front": "Who's that Pokémon?",
        "back": "Onix",
        "extra": "#095 · Rock/Ground",
        "frontImage": "https://raw.githubusercontent.com/PokeAPI/sprites/master/sprites/pokemon/other/official-artwork/95.png"
      },
      "tags": [
        "poke::rock"
      ]
    },
    {
      "key": "drowzee",
      "model": "basic",
      "fields": {
        "front": "Who's that Pokémon?",
        "back": "Drowzee",
        "extra": "#096 · Psychic",
        "frontImage": "https://raw.githubusercontent.com/PokeAPI/sprites/master/sprites/pokemon/other/official-artwork/96.png"
      },
      "tags": [
        "poke::psychic"
      ]
    },
    {
      "key": "hypno",
      "model": "basic",
      "fields": {
        "front": "Who's that Pokémon?",
        "back": "Hypno",
        "extra": "#097 · Psychic",
        "frontImage": "https://raw.githubusercontent.com/PokeAPI/sprites/master/sprites/pokemon/other/official-artwork/97.png"
      },
      "tags": [
        "poke::psychic"
      ]
    },
    {
      "key": "krabby",
      "model": "basic",
      "fields": {
        "front": "Who's that Pokémon?",
        "back": "Krabby",
        "extra": "#098 · Water",
        "frontImage": "https://raw.githubusercontent.com/PokeAPI/sprites/master/sprites/pokemon/other/official-artwork/98.png"
      },
      "tags": [
        "poke::water"
      ]
    },
    {
      "key": "kingler",
      "model": "basic",
      "fields": {
        "front": "Who's that Pokémon?",
        "back": "Kingler",
        "extra": "#099 · Water",
        "frontImage": "https://raw.githubusercontent.com/PokeAPI/sprites/master/sprites/pokemon/other/official-artwork/99.png"
      },
      "tags": [
        "poke::water"
      ]
    },
    {
      "key": "voltorb",
      "model": "basic",
      "fields": {
        "front": "Who's that Pokémon?",
        "back": "Voltorb",
        "extra": "#100 · Electric",
        "frontImage": "https://raw.githubusercontent.com/PokeAPI/sprites/master/sprites/pokemon/other/official-artwork/100.png"
      },
      "tags": [
        "poke::electric"
      ]
    },
    {
      "key": "electrode",
      "model": "basic",
      "fields": {
        "front": "Who's that Pokémon?",
        "back": "Electrode",
        "extra": "#101 · Electric",
        "frontImage": "https://raw.githubusercontent.com/PokeAPI/sprites/master/sprites/pokemon/other/official-artwork/101.png"
      },
      "tags": [
        "poke::electric"
      ]
    },
    {
      "key": "exeggcute",
      "model": "basic",
      "fields": {
        "front": "Who's that Pokémon?",
        "back": "Exeggcute",
        "extra": "#102 · Grass/Psychic",
        "frontImage": "https://raw.githubusercontent.com/PokeAPI/sprites/master/sprites/pokemon/other/official-artwork/102.png"
      },
      "tags": [
        "poke::grass"
      ]
    },
    {
      "key": "exeggutor",
      "model": "basic",
      "fields": {
        "front": "Who's that Pokémon?",
        "back": "Exeggutor",
        "extra": "#103 · Grass/Psychic",
        "frontImage": "https://raw.githubusercontent.com/PokeAPI/sprites/master/sprites/pokemon/other/official-artwork/103.png"
      },
      "tags": [
        "poke::grass"
      ]
    },
    {
      "key": "cubone",
      "model": "basic",
      "fields": {
        "front": "Who's that Pokémon?",
        "back": "Cubone",
        "extra": "#104 · Ground",
        "frontImage": "https://raw.githubusercontent.com/PokeAPI/sprites/master/sprites/pokemon/other/official-artwork/104.png"
      },
      "tags": [
        "poke::ground"
      ]
    },
    {
      "key": "marowak",
      "model": "basic",
      "fields": {
        "front": "Who's that Pokémon?",
        "back": "Marowak",
        "extra": "#105 · Ground",
        "frontImage": "https://raw.githubusercontent.com/PokeAPI/sprites/master/sprites/pokemon/other/official-artwork/105.png"
      },
      "tags": [
        "poke::ground"
      ]
    },
    {
      "key": "hitmonlee",
      "model": "basic",
      "fields": {
        "front": "Who's that Pokémon?",
        "back": "Hitmonlee",
        "extra": "#106 · Fighting",
        "frontImage": "https://raw.githubusercontent.com/PokeAPI/sprites/master/sprites/pokemon/other/official-artwork/106.png"
      },
      "tags": [
        "poke::fighting"
      ]
    },
    {
      "key": "hitmonchan",
      "model": "basic",
      "fields": {
        "front": "Who's that Pokémon?",
        "back": "Hitmonchan",
        "extra": "#107 · Fighting",
        "frontImage": "https://raw.githubusercontent.com/PokeAPI/sprites/master/sprites/pokemon/other/official-artwork/107.png"
      },
      "tags": [
        "poke::fighting"
      ]
    },
    {
      "key": "lickitung",
      "model": "basic",
      "fields": {
        "front": "Who's that Pokémon?",
        "back": "Lickitung",
        "extra": "#108 · Normal",
        "frontImage": "https://raw.githubusercontent.com/PokeAPI/sprites/master/sprites/pokemon/other/official-artwork/108.png"
      },
      "tags": [
        "poke::normal"
      ]
    },
    {
      "key": "koffing",
      "model": "basic",
      "fields": {
        "front": "Who's that Pokémon?",
        "back": "Koffing",
        "extra": "#109 · Poison",
        "frontImage": "https://raw.githubusercontent.com/PokeAPI/sprites/master/sprites/pokemon/other/official-artwork/109.png"
      },
      "tags": [
        "poke::poison"
      ]
    },
    {
      "key": "weezing",
      "model": "basic",
      "fields": {
        "front": "Who's that Pokémon?",
        "back": "Weezing",
        "extra": "#110 · Poison",
        "frontImage": "https://raw.githubusercontent.com/PokeAPI/sprites/master/sprites/pokemon/other/official-artwork/110.png"
      },
      "tags": [
        "poke::poison"
      ]
    },
    {
      "key": "rhyhorn",
      "model": "basic",
      "fields": {
        "front": "Who's that Pokémon?",
        "back": "Rhyhorn",
        "extra": "#111 · Ground/Rock",
        "frontImage": "https://raw.githubusercontent.com/PokeAPI/sprites/master/sprites/pokemon/other/official-artwork/111.png"
      },
      "tags": [
        "poke::ground"
      ]
    },
    {
      "key": "rhydon",
      "model": "basic",
      "fields": {
        "front": "Who's that Pokémon?",
        "back": "Rhydon",
        "extra": "#112 · Ground/Rock",
        "frontImage": "https://raw.githubusercontent.com/PokeAPI/sprites/master/sprites/pokemon/other/official-artwork/112.png"
      },
      "tags": [
        "poke::ground"
      ]
    },
    {
      "key": "chansey",
      "model": "basic",
      "fields": {
        "front": "Who's that Pokémon?",
        "back": "Chansey",
        "extra": "#113 · Normal",
        "frontImage": "https://raw.githubusercontent.com/PokeAPI/sprites/master/sprites/pokemon/other/official-artwork/113.png"
      },
      "tags": [
        "poke::normal"
      ]
    },
    {
      "key": "tangela",
      "model": "basic",
      "fields": {
        "front": "Who's that Pokémon?",
        "back": "Tangela",
        "extra": "#114 · Grass",
        "frontImage": "https://raw.githubusercontent.com/PokeAPI/sprites/master/sprites/pokemon/other/official-artwork/114.png"
      },
      "tags": [
        "poke::grass"
      ]
    },
    {
      "key": "kangaskhan",
      "model": "basic",
      "fields": {
        "front": "Who's that Pokémon?",
        "back": "Kangaskhan",
        "extra": "#115 · Normal",
        "frontImage": "https://raw.githubusercontent.com/PokeAPI/sprites/master/sprites/pokemon/other/official-artwork/115.png"
      },
      "tags": [
        "poke::normal"
      ]
    },
    {
      "key": "horsea",
      "model": "basic",
      "fields": {
        "front": "Who's that Pokémon?",
        "back": "Horsea",
        "extra": "#116 · Water",
        "frontImage": "https://raw.githubusercontent.com/PokeAPI/sprites/master/sprites/pokemon/other/official-artwork/116.png"
      },
      "tags": [
        "poke::water"
      ]
    },
    {
      "key": "seadra",
      "model": "basic",
      "fields": {
        "front": "Who's that Pokémon?",
        "back": "Seadra",
        "extra": "#117 · Water",
        "frontImage": "https://raw.githubusercontent.com/PokeAPI/sprites/master/sprites/pokemon/other/official-artwork/117.png"
      },
      "tags": [
        "poke::water"
      ]
    },
    {
      "key": "goldeen",
      "model": "basic",
      "fields": {
        "front": "Who's that Pokémon?",
        "back": "Goldeen",
        "extra": "#118 · Water",
        "frontImage": "https://raw.githubusercontent.com/PokeAPI/sprites/master/sprites/pokemon/other/official-artwork/118.png"
      },
      "tags": [
        "poke::water"
      ]
    },
    {
      "key": "seaking",
      "model": "basic",
      "fields": {
        "front": "Who's that Pokémon?",
        "back": "Seaking",
        "extra": "#119 · Water",
        "frontImage": "https://raw.githubusercontent.com/PokeAPI/sprites/master/sprites/pokemon/other/official-artwork/119.png"
      },
      "tags": [
        "poke::water"
      ]
    },
    {
      "key": "staryu",
      "model": "basic",
      "fields": {
        "front": "Who's that Pokémon?",
        "back": "Staryu",
        "extra": "#120 · Water",
        "frontImage": "https://raw.githubusercontent.com/PokeAPI/sprites/master/sprites/pokemon/other/official-artwork/120.png"
      },
      "tags": [
        "poke::water"
      ]
    },
    {
      "key": "starmie",
      "model": "basic",
      "fields": {
        "front": "Who's that Pokémon?",
        "back": "Starmie",
        "extra": "#121 · Water/Psychic",
        "frontImage": "https://raw.githubusercontent.com/PokeAPI/sprites/master/sprites/pokemon/other/official-artwork/121.png"
      },
      "tags": [
        "poke::water"
      ]
    },
    {
      "key": "mr-mime",
      "model": "basic",
      "fields": {
        "front": "Who's that Pokémon?",
        "back": "Mr. Mime",
        "extra": "#122 · Psychic/Fairy",
        "frontImage": "https://raw.githubusercontent.com/PokeAPI/sprites/master/sprites/pokemon/other/official-artwork/122.png"
      },
      "tags": [
        "poke::psychic"
      ]
    },
    {
      "key": "scyther",
      "model": "basic",
      "fields": {
        "front": "Who's that Pokémon?",
        "back": "Scyther",
        "extra": "#123 · Bug/Flying",
        "frontImage": "https://raw.githubusercontent.com/PokeAPI/sprites/master/sprites/pokemon/other/official-artwork/123.png"
      },
      "tags": [
        "poke::bug"
      ]
    },
    {
      "key": "jynx",
      "model": "basic",
      "fields": {
        "front": "Who's that Pokémon?",
        "back": "Jynx",
        "extra": "#124 · Ice/Psychic",
        "frontImage": "https://raw.githubusercontent.com/PokeAPI/sprites/master/sprites/pokemon/other/official-artwork/124.png"
      },
      "tags": [
        "poke::ice"
      ]
    },
    {
      "key": "electabuzz",
      "model": "basic",
      "fields": {
        "front": "Who's that Pokémon?",
        "back": "Electabuzz",
        "extra": "#125 · Electric",
        "frontImage": "https://raw.githubusercontent.com/PokeAPI/sprites/master/sprites/pokemon/other/official-artwork/125.png"
      },
      "tags": [
        "poke::electric"
      ]
    },
    {
      "key": "magmar",
      "model": "basic",
      "fields": {
        "front": "Who's that Pokémon?",
        "back": "Magmar",
        "extra": "#126 · Fire",
        "frontImage": "https://raw.githubusercontent.com/PokeAPI/sprites/master/sprites/pokemon/other/official-artwork/126.png"
      },
      "tags": [
        "poke::fire"
      ]
    },
    {
      "key": "pinsir",
      "model": "basic",
      "fields": {
        "front": "Who's that Pokémon?",
        "back": "Pinsir",
        "extra": "#127 · Bug",
        "frontImage": "https://raw.githubusercontent.com/PokeAPI/sprites/master/sprites/pokemon/other/official-artwork/127.png"
      },
      "tags": [
        "poke::bug"
      ]
    },
    {
      "key": "tauros",
      "model": "basic",
      "fields": {
        "front": "Who's that Pokémon?",
        "back": "Tauros",
        "extra": "#128 · Normal",
        "frontImage": "https://raw.githubusercontent.com/PokeAPI/sprites/master/sprites/pokemon/other/official-artwork/128.png"
      },
      "tags": [
        "poke::normal"
      ]
    },
    {
      "key": "magikarp",
      "model": "basic",
      "fields": {
        "front": "Who's that Pokémon?",
        "back": "Magikarp",
        "extra": "#129 · Water",
        "frontImage": "https://raw.githubusercontent.com/PokeAPI/sprites/master/sprites/pokemon/other/official-artwork/129.png"
      },
      "tags": [
        "poke::water"
      ]
    },
    {
      "key": "gyarados",
      "model": "basic",
      "fields": {
        "front": "Who's that Pokémon?",
        "back": "Gyarados",
        "extra": "#130 · Water/Flying",
        "frontImage": "https://raw.githubusercontent.com/PokeAPI/sprites/master/sprites/pokemon/other/official-artwork/130.png"
      },
      "tags": [
        "poke::water"
      ]
    },
    {
      "key": "lapras",
      "model": "basic",
      "fields": {
        "front": "Who's that Pokémon?",
        "back": "Lapras",
        "extra": "#131 · Water/Ice",
        "frontImage": "https://raw.githubusercontent.com/PokeAPI/sprites/master/sprites/pokemon/other/official-artwork/131.png"
      },
      "tags": [
        "poke::water"
      ]
    },
    {
      "key": "ditto",
      "model": "basic",
      "fields": {
        "front": "Who's that Pokémon?",
        "back": "Ditto",
        "extra": "#132 · Normal",
        "frontImage": "https://raw.githubusercontent.com/PokeAPI/sprites/master/sprites/pokemon/other/official-artwork/132.png"
      },
      "tags": [
        "poke::normal"
      ]
    },
    {
      "key": "eevee",
      "model": "basic",
      "fields": {
        "front": "Who's that Pokémon?",
        "back": "Eevee",
        "extra": "#133 · Normal",
        "frontImage": "https://raw.githubusercontent.com/PokeAPI/sprites/master/sprites/pokemon/other/official-artwork/133.png"
      },
      "tags": [
        "poke::normal"
      ]
    },
    {
      "key": "vaporeon",
      "model": "basic",
      "fields": {
        "front": "Who's that Pokémon?",
        "back": "Vaporeon",
        "extra": "#134 · Water",
        "frontImage": "https://raw.githubusercontent.com/PokeAPI/sprites/master/sprites/pokemon/other/official-artwork/134.png"
      },
      "tags": [
        "poke::water"
      ]
    },
    {
      "key": "jolteon",
      "model": "basic",
      "fields": {
        "front": "Who's that Pokémon?",
        "back": "Jolteon",
        "extra": "#135 · Electric",
        "frontImage": "https://raw.githubusercontent.com/PokeAPI/sprites/master/sprites/pokemon/other/official-artwork/135.png"
      },
      "tags": [
        "poke::electric"
      ]
    },
    {
      "key": "flareon",
      "model": "basic",
      "fields": {
        "front": "Who's that Pokémon?",
        "back": "Flareon",
        "extra": "#136 · Fire",
        "frontImage": "https://raw.githubusercontent.com/PokeAPI/sprites/master/sprites/pokemon/other/official-artwork/136.png"
      },
      "tags": [
        "poke::fire"
      ]
    },
    {
      "key": "porygon",
      "model": "basic",
      "fields": {
        "front": "Who's that Pokémon?",
        "back": "Porygon",
        "extra": "#137 · Normal",
        "frontImage": "https://raw.githubusercontent.com/PokeAPI/sprites/master/sprites/pokemon/other/official-artwork/137.png"
      },
      "tags": [
        "poke::normal"
      ]
    },
    {
      "key": "omanyte",
      "model": "basic",
      "fields": {
        "front": "Who's that Pokémon?",
        "back": "Omanyte",
        "extra": "#138 · Rock/Water",
        "frontImage": "https://raw.githubusercontent.com/PokeAPI/sprites/master/sprites/pokemon/other/official-artwork/138.png"
      },
      "tags": [
        "poke::rock"
      ]
    },
    {
      "key": "omastar",
      "model": "basic",
      "fields": {
        "front": "Who's that Pokémon?",
        "back": "Omastar",
        "extra": "#139 · Rock/Water",
        "frontImage": "https://raw.githubusercontent.com/PokeAPI/sprites/master/sprites/pokemon/other/official-artwork/139.png"
      },
      "tags": [
        "poke::rock"
      ]
    },
    {
      "key": "kabuto",
      "model": "basic",
      "fields": {
        "front": "Who's that Pokémon?",
        "back": "Kabuto",
        "extra": "#140 · Rock/Water",
        "frontImage": "https://raw.githubusercontent.com/PokeAPI/sprites/master/sprites/pokemon/other/official-artwork/140.png"
      },
      "tags": [
        "poke::rock"
      ]
    },
    {
      "key": "kabutops",
      "model": "basic",
      "fields": {
        "front": "Who's that Pokémon?",
        "back": "Kabutops",
        "extra": "#141 · Rock/Water",
        "frontImage": "https://raw.githubusercontent.com/PokeAPI/sprites/master/sprites/pokemon/other/official-artwork/141.png"
      },
      "tags": [
        "poke::rock"
      ]
    },
    {
      "key": "aerodactyl",
      "model": "basic",
      "fields": {
        "front": "Who's that Pokémon?",
        "back": "Aerodactyl",
        "extra": "#142 · Rock/Flying",
        "frontImage": "https://raw.githubusercontent.com/PokeAPI/sprites/master/sprites/pokemon/other/official-artwork/142.png"
      },
      "tags": [
        "poke::rock"
      ]
    },
    {
      "key": "snorlax",
      "model": "basic",
      "fields": {
        "front": "Who's that Pokémon?",
        "back": "Snorlax",
        "extra": "#143 · Normal",
        "frontImage": "https://raw.githubusercontent.com/PokeAPI/sprites/master/sprites/pokemon/other/official-artwork/143.png"
      },
      "tags": [
        "poke::normal"
      ]
    },
    {
      "key": "articuno",
      "model": "basic",
      "fields": {
        "front": "Who's that Pokémon?",
        "back": "Articuno",
        "extra": "#144 · Ice/Flying",
        "frontImage": "https://raw.githubusercontent.com/PokeAPI/sprites/master/sprites/pokemon/other/official-artwork/144.png"
      },
      "tags": [
        "poke::ice"
      ]
    },
    {
      "key": "zapdos",
      "model": "basic",
      "fields": {
        "front": "Who's that Pokémon?",
        "back": "Zapdos",
        "extra": "#145 · Electric/Flying",
        "frontImage": "https://raw.githubusercontent.com/PokeAPI/sprites/master/sprites/pokemon/other/official-artwork/145.png"
      },
      "tags": [
        "poke::electric"
      ]
    },
    {
      "key": "moltres",
      "model": "basic",
      "fields": {
        "front": "Who's that Pokémon?",
        "back": "Moltres",
        "extra": "#146 · Fire/Flying",
        "frontImage": "https://raw.githubusercontent.com/PokeAPI/sprites/master/sprites/pokemon/other/official-artwork/146.png"
      },
      "tags": [
        "poke::fire"
      ]
    },
    {
      "key": "dratini",
      "model": "basic",
      "fields": {
        "front": "Who's that Pokémon?",
        "back": "Dratini",
        "extra": "#147 · Dragon",
        "frontImage": "https://raw.githubusercontent.com/PokeAPI/sprites/master/sprites/pokemon/other/official-artwork/147.png"
      },
      "tags": [
        "poke::dragon"
      ]
    },
    {
      "key": "dragonair",
      "model": "basic",
      "fields": {
        "front": "Who's that Pokémon?",
        "back": "Dragonair",
        "extra": "#148 · Dragon",
        "frontImage": "https://raw.githubusercontent.com/PokeAPI/sprites/master/sprites/pokemon/other/official-artwork/148.png"
      },
      "tags": [
        "poke::dragon"
      ]
    },
    {
      "key": "dragonite",
      "model": "basic",
      "fields": {
        "front": "Who's that Pokémon?",
        "back": "Dragonite",
        "extra": "#149 · Dragon/Flying",
        "frontImage": "https://raw.githubusercontent.com/PokeAPI/sprites/master/sprites/pokemon/other/official-artwork/149.png"
      },
      "tags": [
        "poke::dragon"
      ]
    },
    {
      "key": "mewtwo",
      "model": "basic",
      "fields": {
        "front": "Who's that Pokémon?",
        "back": "Mewtwo",
        "extra": "#150 · Psychic",
        "frontImage": "https://raw.githubusercontent.com/PokeAPI/sprites/master/sprites/pokemon/other/official-artwork/150.png"
      },
      "tags": [
        "poke::psychic"
      ]
    },
    {
      "key": "mew",
      "model": "basic",
      "fields": {
        "front": "Who's that Pokémon?",
        "back": "Mew",
        "extra": "#151 · Psychic",
        "frontImage": "https://raw.githubusercontent.com/PokeAPI/sprites/master/sprites/pokemon/other/official-artwork/151.png"
      },
      "tags": [
        "poke::psychic"
      ]
    }
  ]
}
